deepdrift/__init__.py
deepdrift/doctor.py
deepdrift/guard.py
deepdrift/monitor.py
deepdrift/observer.py
deepdrift/router.py
deepdrift/vision.py
deepdrift/visualization.py
deepdrift-1.0.0.dist-info/licenses/LICENSE
deepdrift-1.0.0.dist-info/METADATA
deepdrift-1.0.0.dist-info/WHEEL
deepdrift-1.0.0.dist-info/top_level.txt
deepdrift-1.0.0.dist-info/RECORD
