Metadata-Version: 2.4
Name: deepdrift
Version: 1.0.0
Summary: Universal Thermodynamic Framework for Neural Network Robustness (Vision, LLM, Router)
Home-page: https://github.com/Eutonics/DeepDrift
Author: Alexey Evtushenko
Author-email: alexey@eutonics.ru
Keywords: llm hallucination detection,vision robustness,ood detection,semantic velocity
Classifier: Programming Language :: Python :: 3
Classifier: License :: OSI Approved :: MIT License
Classifier: Topic :: Scientific/Engineering :: Artificial Intelligence
Classifier: Intended Audience :: Developers
Classifier: Intended Audience :: Science/Research
License-File: LICENSE
Requires-Dist: torch>=2.0.0
Requires-Dist: transformers>=4.30.0
Requires-Dist: numpy
Requires-Dist: matplotlib
Dynamic: author
Dynamic: author-email
Dynamic: classifier
Dynamic: description
Dynamic: description-content-type
Dynamic: home-page
Dynamic: keywords
Dynamic: license-file
Dynamic: requires-dist
Dynamic: summary
